infuse/__init__.py
infuse/app.py
infuse/config.py
infuse/errors.py
infuse/patch.py
infuse/utils.py
infuse/breaker/__init__.py
infuse/breaker/states.py
infuse/breaker/storages.py
insanic_infuse-0.4.0.dist-info/LICENSE
insanic_infuse-0.4.0.dist-info/METADATA
insanic_infuse-0.4.0.dist-info/WHEEL
insanic_infuse-0.4.0.dist-info/top_level.txt
insanic_infuse-0.4.0.dist-info/RECORD
