Metadata-Version: 2.1
Name: insanic-infuse
Version: 0.4.0
Summary: Async circuit breaker implementation for Insanic
Home-page: https://github.com/crazytruth/infuse
Author: Kwang Jin Kim
Author-email: kwangjinkim@gmail.com
License: MIT
Keywords: circuit breaker async asyncio microservice
Platform: UNKNOWN
Classifier: Development Status :: 3 - Alpha
Classifier: License :: OSI Approved :: MIT License
Classifier: Programming Language :: Python :: 3.6
Classifier: Programming Language :: Python :: 3.7
Classifier: Programming Language :: Python :: 3.8
Requires-Dist: insanic-framework (<0.10,>=0.9.0)
Requires-Dist: pybreaker
Requires-Dist: wrapt
